qr.py
setup.py
qr.egg-info/PKG-INFO
qr.egg-info/SOURCES.txt
qr.egg-info/dependency_links.txt
qr.egg-info/not-zip-safe
qr.egg-info/top_level.txt
test/__init__.py
test/tests.py