Metadata-Version: 1.0
Name: qr
Version: 0.6.0
Summary: Redis-powered queues, capped collections, deques, and stacks
Home-page: http://github.com/tnm/qr
Author: Ted Nyman
Author-email: ted@ted.io
License: MIT
Keywords: Redis,queue,data structures
Platform: UNKNOWN
Classifier: Programming Language :: Python
Classifier: Intended Audience :: Developers
Classifier: License :: OSI Approved :: MIT License
Classifier: Operating System :: OS Independent
